ytmdpy/__init__.py
ytmdpy/client.py
ytmdpy/enums.py
ytmdpy/exceptions.py
ytmdpy/http.py
ytmdpy-1.0.0.dist-info/LICENSE
ytmdpy-1.0.0.dist-info/METADATA
ytmdpy-1.0.0.dist-info/WHEEL
ytmdpy-1.0.0.dist-info/top_level.txt
ytmdpy-1.0.0.dist-info/RECORD
