Metadata-Version: 2.2
Name: ytmdpy
Version: 1.0.0
Summary: Youtube Music Desktop API Wrapper
Author-email: Isabelle Phoebe <hi@uwu.gal>
License: MIT License
Project-URL: Homepage, https://github.com/ijsbol/ytmdpy
Project-URL: Bug Tracker, https://github.com/ijsbol/ytmdpy/issues
Classifier: Development Status :: 5 - Production/Stable
Classifier: License :: OSI Approved :: MIT License
Classifier: Intended Audience :: Developers
Classifier: Natural Language :: English
Classifier: Operating System :: OS Independent
Classifier: Programming Language :: Python :: 3.8
Classifier: Programming Language :: Python :: 3.9
Classifier: Programming Language :: Python :: 3.10
Classifier: Programming Language :: Python :: 3.11
Classifier: Programming Language :: Python :: 3.12
Classifier: Topic :: Internet
Classifier: Topic :: Software Development :: Libraries
Classifier: Topic :: Software Development :: Libraries :: Python Modules
Classifier: Topic :: Utilities
Classifier: Typing :: Typed
License-File: LICENSE
Requires-Dist: aiohttp
